README.md
setup.cfg
setup.py
auchanTestTools/__init__.py
auchanTestTools/testing_tools.py
auchanTestTools.egg-info/PKG-INFO
auchanTestTools.egg-info/SOURCES.txt
auchanTestTools.egg-info/dependency_links.txt
auchanTestTools.egg-info/requires.txt
auchanTestTools.egg-info/top_level.txt